YuanzeZhongwenban/README.md
YuanzeZhongwenban/__init__.py
YuanzeZhongwenban/__main__.py
YuanzeZhongwenban/file.epub
YuanzeZhongwenban/index.html
YuanzeZhongwenban/css/__init__.py
YuanzeZhongwenban/css/annotations.css
YuanzeZhongwenban/css/main.css
YuanzeZhongwenban/css/normalize.css
YuanzeZhongwenban/css/popup.css
YuanzeZhongwenban/font/__init__.py
YuanzeZhongwenban/font/fontello.eot
YuanzeZhongwenban/font/fontello.svg
YuanzeZhongwenban/font/fontello.ttf
YuanzeZhongwenban/font/fontello.woff
YuanzeZhongwenban/img/__init__.py
YuanzeZhongwenban/img/annotator-glyph-sprite.png
YuanzeZhongwenban/img/annotator-icon-sprite.png
YuanzeZhongwenban/img/apple-touch-icon.png
YuanzeZhongwenban/img/cancelfullscreen.png
YuanzeZhongwenban/img/close.png
YuanzeZhongwenban/img/fullscreen.png
YuanzeZhongwenban/img/loader.gif
YuanzeZhongwenban/img/menu-icon.png
YuanzeZhongwenban/img/save.png
YuanzeZhongwenban/img/saved.png
YuanzeZhongwenban/img/settings-s.png
YuanzeZhongwenban/img/settings.png
YuanzeZhongwenban/img/star.png
YuanzeZhongwenban/js/__init__.py
YuanzeZhongwenban/js/epub.js
YuanzeZhongwenban/js/epub.min.js
YuanzeZhongwenban/js/epub.min.map
YuanzeZhongwenban/js/hooks.min.js
YuanzeZhongwenban/js/hooks.min.map
YuanzeZhongwenban/js/reader.js
YuanzeZhongwenban/js/reader.js.map
YuanzeZhongwenban/js/reader.min.js
YuanzeZhongwenban/js/reader.min.map
YuanzeZhongwenban/js/hooks/__init__.py
YuanzeZhongwenban/js/hooks/extensions/__init__.py
YuanzeZhongwenban/js/hooks/extensions/highlight.js
YuanzeZhongwenban/js/libs/__init__.py
YuanzeZhongwenban/js/libs/jquery.min.js
YuanzeZhongwenban/js/libs/localforage.min.js
YuanzeZhongwenban/js/libs/screenfull.js
YuanzeZhongwenban/js/libs/screenfull.min.js
YuanzeZhongwenban/js/libs/zip.min.js
YuanzeZhongwenban/js/plugins/__init__.py
YuanzeZhongwenban/js/plugins/hypothesis.js
YuanzeZhongwenban/js/plugins/search.js
yuanze_zhongwenban-2024.3.5.0.dist-info/METADATA
yuanze_zhongwenban-2024.3.5.0.dist-info/WHEEL
yuanze_zhongwenban-2024.3.5.0.dist-info/entry_points.txt
yuanze_zhongwenban-2024.3.5.0.dist-info/top_level.txt
yuanze_zhongwenban-2024.3.5.0.dist-info/RECORD
